planet_lib/__init__.py
planet_lib/ascii_converter.py
planet_lib/discord_bot.py
planet_lib/logger.py
planet_lib/math_utils.py
planet_lib-0.1.dist-info/LICENSE
planet_lib-0.1.dist-info/METADATA
planet_lib-0.1.dist-info/WHEEL
planet_lib-0.1.dist-info/top_level.txt
planet_lib-0.1.dist-info/RECORD
