Metadata-Version: 2.1
Name: planet_lib
Version: 0.1
Summary: Una libreria multiuso
Author: Simoo_
Author-email: simonecardella8@gmail.com
Classifier: Programming Language :: Python :: 3
Classifier: License :: OSI Approved :: MIT License
Classifier: Operating System :: OS Independent
Requires-Python: >=3.6
License-File: LICENSE
Requires-Dist: discord.py
